langsmith_cli/__init__.py
langsmith_cli/__main__.py
langsmith_cli/cli.py
langsmith_cli/config.py
langsmith_cli/fetchers.py
langsmith_cli/formatters.py
langsmith_fetch-0.3.1.dist-info/METADATA
langsmith_fetch-0.3.1.dist-info/WHEEL
langsmith_fetch-0.3.1.dist-info/entry_points.txt
langsmith_fetch-0.3.1.dist-info/RECORD
