Metadata-Version: 2.4
Name: langsmith-fetch
Version: 0.3.1
Summary: LangSmith Fetch - Minimal CLI for fetching LangSmith threads and traces
Requires-Python: >=3.10
Requires-Dist: click>=8.0
Requires-Dist: langsmith>=0.1.0
Requires-Dist: python-dotenv>=1.0
Requires-Dist: pyyaml>=6.0
Requires-Dist: requests>=2.31
Requires-Dist: rich>=13.0
Provides-Extra: dev
Requires-Dist: ruff>=0.1.0; extra == 'dev'
Provides-Extra: test
Requires-Dist: pytest-mock>=3.12; extra == 'test'
Requires-Dist: pytest>=7.0; extra == 'test'
Requires-Dist: responses>=0.24; extra == 'test'
